setup.py
mec_translator.egg-info/PKG-INFO
mec_translator.egg-info/SOURCES.txt
mec_translator.egg-info/dependency_links.txt
mec_translator.egg-info/entry_points.txt
mec_translator.egg-info/not-zip-safe
mec_translator.egg-info/top_level.txt
translator/__init__.py
translator/translator.py