Metadata-Version: 1.0
Name: mec-translator
Version: 0.0.4
Summary: A command line translator powered by Youdao api
Home-page: https://github.com/mecforlove/translator
Author: mec
Author-email: mecforlove@outlook.com
License: Apache
Platform: any
